[
  {
    "ContainingType": "ProductApi.Controllers.ProductController",
    "Method": "GetProducts",
    "RelativePath": "api/Product",
    "HttpMethod": "GET",
    "IsController": true,
    "Order": 0,
    "Parameters": [],
    "ReturnTypes": []
  },
  {
    "ContainingType": "ProductApi.Controllers.ProductController",
    "Method": "AddProduct",
    "RelativePath": "api/Product",
    "HttpMethod": "POST",
    "IsController": true,
    "Order": 0,
    "Parameters": [
      {
        "Name": "dto",
        "Type": "ProductApi.DTOs.ProductDto",
        "IsRequired": true
      }
    ],
    "ReturnTypes": []
  },
  {
    "ContainingType": "ProductApi.Controllers.ProductController",
    "Method": "UpdateProduct",
    "RelativePath": "api/Product/{id}",
    "HttpMethod": "PUT",
    "IsController": true,
    "Order": 0,
    "Parameters": [
      {
        "Name": "id",
        "Type": "System.Int32",
        "IsRequired": true
      },
      {
        "Name": "dto",
        "Type": "ProductApi.DTOs.ProductDto",
        "IsRequired": true
      }
    ],
    "ReturnTypes": []
  },
  {
    "ContainingType": "ProductApi.Controllers.ProductController",
    "Method": "DeleteProduct",
    "RelativePath": "api/Product/{id}",
    "HttpMethod": "DELETE",
    "IsController": true,
    "Order": 0,
    "Parameters": [
      {
        "Name": "id",
        "Type": "System.Int32",
        "IsRequired": true
      },
      {
        "Name": "DeletedProduct",
        "Type": "ProductApi.Models.Product",
        "IsRequired": true
      }
    ],
    "ReturnTypes": []
  }
]